ncbi_taxonomist-1.2.1.data/scripts/ncbi-taxonomist
ncbitaxonomist/VERSION
ncbitaxonomist/VERSION.pypi
ncbitaxonomist/__init__.py
ncbitaxonomist/collector.py
ncbitaxonomist/config.py
ncbitaxonomist/groupmanager.py
ncbitaxonomist/mapper.py
ncbitaxonomist/ncbitaxonomist.py
ncbitaxonomist/utils.py
ncbitaxonomist/analyzer/__init__.py
ncbitaxonomist/analyzer/accession.py
ncbitaxonomist/analyzer/collect.py
ncbitaxonomist/analyzer/mapping.py
ncbitaxonomist/analyzer/resolve.py
ncbitaxonomist/cache/__init__.py
ncbitaxonomist/cache/accession.py
ncbitaxonomist/cache/cache.py
ncbitaxonomist/cache/taxa.py
ncbitaxonomist/convert/__init__.py
ncbitaxonomist/convert/accessiondb.py
ncbitaxonomist/convert/converter.py
ncbitaxonomist/convert/convertermap.py
ncbitaxonomist/convert/ncbiaccession.py
ncbitaxonomist/convert/ncbitaxon.py
ncbitaxonomist/convert/taxadb.py
ncbitaxonomist/db/__init__.py
ncbitaxonomist/db/dbimporter.py
ncbitaxonomist/db/dbmanager.py
ncbitaxonomist/db/table/__init__.py
ncbitaxonomist/db/table/accessions.py
ncbitaxonomist/db/table/basetable.py
ncbitaxonomist/db/table/groups.py
ncbitaxonomist/db/table/names.py
ncbitaxonomist/db/table/taxa.py
ncbitaxonomist/entrezresult/__init__.py
ncbitaxonomist/entrezresult/accession.py
ncbitaxonomist/entrezresult/mapping.py
ncbitaxonomist/entrezresult/taxonomy.py
ncbitaxonomist/formatter/__init__.py
ncbitaxonomist/formatter/base.py
ncbitaxonomist/formatter/jsonformatter.py
ncbitaxonomist/formatter/xmlformatter.py
ncbitaxonomist/log/__init__.py
ncbitaxonomist/log/conf.py
ncbitaxonomist/log/logger.py
ncbitaxonomist/model/__init__.py
ncbitaxonomist/model/accession.py
ncbitaxonomist/model/datamodel.py
ncbitaxonomist/model/taxon.py
ncbitaxonomist/parser/__init__.py
ncbitaxonomist/parser/arguments.py
ncbitaxonomist/parser/group.py
ncbitaxonomist/parser/stdout.py
ncbitaxonomist/parser/ncbi/__init__.py
ncbitaxonomist/parser/ncbi/ncbitaxon.py
ncbitaxonomist/parser/ncbi/taxonomy.py
ncbitaxonomist/payload/__init__.py
ncbi_taxonomist-1.2.1.dist-info/LICENSE
ncbi_taxonomist-1.2.1.dist-info/METADATA
ncbi_taxonomist-1.2.1.dist-info/WHEEL
ncbi_taxonomist-1.2.1.dist-info/top_level.txt
ncbi_taxonomist-1.2.1.dist-info/RECORD
