Metadata-Version: 2.1
Name: ncbi-taxonomist
Version: 1.2.1
Summary: Toolbox to manage NCBI taxonomical data
Home-page: https://gitlab.com/janpb/ncbi-taxonomist.git
Author: Jan P Buchmann
Author-email: jpb@members.fsf.org
License: LGPL
Project-URL: Doc, https://ncbi-taxonomist.readthedocs.io/
Project-URL: Code, https://gitlab.com/janpb/ncbi-taxonomist.git
Keywords: bioinformatics NCBI taxonomy
Platform: UNKNOWN
Classifier: Programming Language :: Python :: 3.8
Classifier: Operating System :: OS Independent
Classifier: Development Status :: 5 - Production/Stable
Classifier: Environment :: Console
Classifier: Intended Audience :: Science/Research
Classifier: License :: OSI Approved :: GNU General Public License v3 or later (GPLv3+)
Classifier: Topic :: Scientific/Engineering :: Bio-Informatics
Classifier: Topic :: Scientific/Engineering :: Information Analysis
Requires-Python: >=3.8
Requires-Dist: entrezpy (>=2.1.0)
